Metadata-Version: 2.1
Name: cordex
Version: 1.0.0
Summary: Parser for collocability
Home-page: https://github.com/clarinsi/cordex
Author: CJVT
Author-email: pypi@cjvt.si
License: MIT
License-File: LICENSE
Requires-Dist: conllu>=4.5.2
Requires-Dist: cjvt-conversion-utils>=0.3
Requires-Dist: importlib-resources>=5.4.0
Requires-Dist: lxml>=4.9.1
Requires-Dist: tqdm>=4.62.3
Requires-Dist: zipp>=3.6.0
Requires-Dist: requests>=2.21.0
